{"trial_id": "16", "hyperparameters": {"space": [{"class_name": "Int", "config": {"name": "conv_filters", "default": null, "conditions": [], "min_value": 16, "max_value": 64, "step": 16, "sampling": "linear"}}, {"class_name": "Int", "config": {"name": "dense_units", "default": null, "conditions": [], "min_value": 64, "max_value": 256, "step": 64, "sampling": "linear"}}, {"class_name": "Int", "config": {"name": "conv_filters_1", "default": null, "conditions": [], "min_value": 16, "max_value": 128, "step": 16, "sampling": "linear"}}, {"class_name": "Int", "config": {"name": "dense_units_1", "default": null, "conditions": [], "min_value": 64, "max_value": 256, "step": 64, "sampling": "linear"}}], "values": {"conv_filters": 48, "dense_units": 128, "conv_filters_1": 16, "dense_units_1": 192}}, "metrics": {"metrics": {"loss": {"direction": "min", "observations": [{"value": [0.11919144541025162], "step": 7}]}, "accuracy": {"direction": "max", "observations": [{"value": [0.9555555582046509], "step": 7}]}, "val_loss": {"direction": "min", "observations": [{"value": [0.5662362575531006], "step": 7}]}, "val_accuracy": {"direction": "max", "observations": [{"value": [0.8166666626930237], "step": 7}]}}}, "score": 0.8166666626930237, "best_step": 7, "status": "COMPLETED", "message": null}